{
  "appetizers": [
    {
      "name": "Bruschetta",
      "description": "",
      "price": 7.99
    }
  ],
  "mains": [
    {
      "name": "Risotto ai Funghi",
      "description": "Traditional italian dish made of rice, mushrooms, shallots, white wine, and some Parmesan cheese.",
      "price": 13.95
    },
    {
      "name": "Pizza Margherita",
      "description": "Our signature crust topped with tomato sauce, mozzarella, and our restaurant's fresh basil.",
      "price": 13.95
    },
    {
      "name": "Spaghetti alla Carbonara",
      "description": "",
      "price": 12.95
    }
  ],
  "sides": [
    {
      "name": "Focaccia",
      "description": "",
      "price": 8.95
    }
  ]
}
